gtrxl_torch/__init__.py
gtrxl_torch/gtrxl_torch.py
gtrxl_torch-0.1.7.dist-info/LICENSE
gtrxl_torch-0.1.7.dist-info/METADATA
gtrxl_torch-0.1.7.dist-info/WHEEL
gtrxl_torch-0.1.7.dist-info/top_level.txt
gtrxl_torch-0.1.7.dist-info/RECORD
