Metadata-Version: 2.1
Name: gtrxl-torch
Version: 0.1.7
Summary: Gated-Transformer XL - PyTorch
Home-page: https://github.com/alantess/gtrxl-torch
Author: Alan Tessier
Author-email: alantessier97@gmail.com
License: MIT
Keywords: transformer,computer vision,deep learning,artifical intelligence
Platform: UNKNOWN
Classifier: Development Status :: 4 - Beta
Classifier: Intended Audience :: Developers
Classifier: Topic :: Scientific/Engineering :: Artificial Intelligence
Classifier: License :: OSI Approved :: MIT License
Classifier: Programming Language :: Python :: 3.6
Requires-Dist: torch (>=1.6)
